{
  "version": 2,
  "savedAt": "2026-07-19T16:04:23.164Z",
  "wasInWizard": true,
  "activeTab": "creator",
  "activeProject": "Ralph_Narration_Button",
  "creatorStep": 1,
  "nicheInput": "engenharia histórica",
  "formatSelector": "SHORTS",
  "ideasData": null,
  "selectedIdeaIndex": -1,
  "generatedScriptData": {
    "strategy": {
      "title_main": "",
      "title_variations": [],
      "hook": "",
      "target_audience": "",
      "tone": "",
      "pinned_comment": "",
      "cta": ""
    },
    "narrative_script": "",
    "narrative_script_tagged": "",
    "visual_prompts": [],
    "checklist": {
      "click_potential": 0,
      "retention_potential": 0,
      "comments_potential": 0,
      "feedback": ""
    }
  },
  "creatorProjectName": "Ralph_Narration_Button",
  "creatorScript": "",
  "ideationTab": "custom",
  "historicalWitnessContext": null,
  "customTitle": "Como os romanos erguiam pedras gigantes",
  "customHooks": "O mecanismo parecia impossível.",
  "customOutline": "Explicar roldanas, vantagem mecânica e travas.",
  "customBlocks": [
    {
      "block": 1,
      "content": "Mostrar o mecanismo real."
    }
  ],
  "customIdeaTitle": "",
  "customIdeaPromise": "",
  "customIdeaHook": "",
  "customIdeaEmotion": "",
  "customIdeaBlocks": "",
  "listNiche": "",
  "listTopic": "",
  "rankCount": 20,
  "rankOrder": "desc",
  "listicleHudStyle": "auto",
  "listicleIdeasData": null,
  "listicleSearchNiche": "",
  "ideasSearchNiche": "",
  "selectedListicleIdeaIndex": -1,
  "showNarrationReview": false,
  "narrationDraft": "",
  "narrationTaggedDraft": "",
  "narrationStrategy": null,
  "narrationBlockPhrases": [],
  "narrationBlockScript": "",
  "narrationNotebooklmEnriched": false,
  "narrationProjectName": "",
  "notebooklmSession": null,
  "useNotebooklm": false,
  "notebooklmDeep": false,
  "useDeepResearch": false,
  "uploadedScenes": {},
  "expandedBlocks": {
    "1": true
  },
  "editorialIdeaImport": null
}
